{
  "target_id": "shrinkage-plot",
  "root_id": "61562",
  "doc": {
    "defs": [],
    "roots": {
      "references": [
        {
          "attributes": {
            "below": [
              {
                "id": "61573"
              }
            ],
            "center": [
              {
                "id": "61576"
              },
              {
                "id": "61580"
              },
              {
                "id": "61611"
              },
              {
                "id": "61614"
              },
              {
                "id": "61686"
              },
              {
                "id": "61689"
              },
              {
                "id": "61692"
              },
              {
                "id": "61695"
              },
              {
                "id": "61698"
              },
              {
                "id": "61701"
              },
              {
                "id": "61704"
              },
              {
                "id": "61707"
              },
              {
                "id": "61710"
              },
              {
                "id": "61713"
              },
              {
                "id": "61716"
              },
              {
                "id": "61719"
              },
              {
                "id": "61722"
              },
              {
                "id": "61725"
              },
              {
                "id": "61728"
              },
              {
                "id": "61731"
              },
              {
                "id": "61734"
              },
              {
                "id": "61737"
              }
            ],
            "height": 500,
            "left": [
              {
                "id": "61577"
              }
            ],
            "outline_line_color": "black",
            "renderers": [
              {
                "id": "61599"
              },
              {
                "id": "61620"
              },
              {
                "id": "61641"
              },
              {
                "id": "61664"
              }
            ],
            "title": {
              "id": "61563"
            },
            "toolbar": {
              "id": "61588"
            },
            "width": 500,
            "x_range": {
              "id": "61565"
            },
            "x_scale": {
              "id": "61569"
            },
            "y_range": {
              "id": "61567"
            },
            "y_scale": {
              "id": "61571"
            }
          },
          "id": "61562",
          "subtype": "Figure",
          "type": "Plot"
        },
        {
          "attributes": {},
          "id": "66234",
          "type": "UnionRenderers"
        },
        {
          "attributes": {
            "line_alpha": 0.1,
            "line_color": "grey",
            "line_width": 2.0,
            "x": {
              "field": "x"
            },
            "y": {
              "field": "y"
            }
          },
          "id": "61618",
          "type": "Line"
        },
        {
          "attributes": {
            "size": {
              "value": 10
            }
          },
          "id": "61694",
          "type": "VeeHead"
        },
        {
          "attributes": {},
          "id": "66235",
          "type": "Selection"
        },
        {
          "attributes": {},
          "id": "61607",
          "type": "AllLabels"
        },
        {
          "attributes": {
            "data": {},
            "selected": {
              "id": "66245"
            },
            "selection_policy": {
              "id": "66244"
            }
          },
          "id": "66209",
          "type": "ColumnDataSource"
        },
        {
          "attributes": {
            "data": {},
            "selected": {
              "id": "66243"
            },
            "selection_policy": {
              "id": "66242"
            }
          },
          "id": "66208",
          "type": "ColumnDataSource"
        },
        {
          "attributes": {
            "data": {
              "name": [
                "Roberto Clemente",
                "Frank Robinson",
                "Frank Howard",
                "Jay Johnstone",
                "Ken Berry",
                "Jim Spencer",
                "Don Kessinger",
                "Luis Alvarado",
                "Ron Santo",
                "Ron Swaboda",
                "Rico Petrocelli",
                "Ellie Rodriguez",
                "George Scott",
                "Del Unser",
                "Billy Williams",
                "Bert Campaneris",
                "Thurman Munson",
                "Max Alvis"
              ],
              "x": {
                "__ndarray__": "mpmZmZmZ2T/Ygi3Ygi3YPxdswRZswdY/VVVVVVVV1T+UPumTPunTP5Q+6ZM+6dM/0id90id90j8RERERERHRP5/0SZ/0Sc8/n/RJn/RJzz8cx3Ecx3HMPxzHcRzHccw/HMdxHMdxzD8cx3Ecx3HMPxzHcRzHccw/mpmZmZmZyT8XbMEWbMHGP5Q+6ZM+6cM/",
                "dtype": "float64",
                "order": "little",
                "shape": [
                  18
                ]
              },
              "y": {
                "__ndarray__": "PZtVn6ut1D/3Bl+YTBXUPznWxW00gNM/LpCg+DHm0j8jSnuDL0zSPxKDwMqhRdI/GQRWDi2y0T9b07zjFB3RP7dif9k9edA/exSuR+F60D+94xQdyeXPPzSAt0CC4s8/io7k8h/Szz+KjuTyH9LPPyS5/If0288/hslUwaikzj8KaCJseHrNP+QUHcnlP8w/",
                "dtype": "float64",
                "order": "little",
                "shape": [
                  18
                ]
              }
            },
            "selected": {
              "id": "61655"
            },
            "selection_policy": {
              "id": "61654"
            }
          },
          "id": "61560",
          "type": "ColumnDataSource"
        },
        {
          "attributes": {
            "base": {
              "field": "x"
            },
            "coordinates": null,
            "fill_alpha": 0.2,
            "fill_color": "orange",
            "group": null,
            "level": "underlay",
            "line_color": "orange",
            "line_width": 0.2,
            "lower": {
              "field": "lower_std"
            },
            "source": {
              "id": "61613"
            },
            "upper": {
              "field": "upper_std"
            }
          },
          "id": "61614",
          "type": "Band"
        },
        {
          "attributes": {
            "data": {},
            "selected": {
              "id": "66247"
            },
            "selection_policy": {
              "id": "66246"
            }
          },
          "id": "66210",
          "type": "ColumnDataSource"
        },
        {
          "attributes": {},
          "id": "66236",
          "type": "UnionRenderers"
        },
        {
          "attributes": {},
          "id": "66237",
          "type": "Selection"
        },
        {
          "attributes": {},
          "id": "61609",
          "type": "Selection"
        },
        {
          "attributes": {
            "size": {
              "value": 10
            }
          },
          "id": "61730",
          "type": "VeeHead"
        },
        {
          "attributes": {
            "coordinates": null,
            "end": {
              "id": "61709"
            },
            "group": null,
            "source": {
              "id": "66211"
            },
            "start": null,
            "x_end": {
              "value": 0.24444444444444444
            },
            "x_start": {
              "value": 0.24444444444444444
            },
            "y_end": {
              "value": 0.2574
            },
            "y_start": {
              "value": 0.255
            }
          },
          "id": "61710",
          "type": "Arrow"
        },
        {
          "attributes": {
            "data": {},
            "selected": {
              "id": "66241"
            },
            "selection_policy": {
              "id": "66240"
            }
          },
          "id": "66207",
          "type": "ColumnDataSource"
        },
        {
          "attributes": {},
          "id": "61631",
          "type": "UnionRenderers"
        },
        {
          "attributes": {},
          "id": "66238",
          "type": "UnionRenderers"
        },
        {
          "attributes": {},
          "id": "66239",
          "type": "Selection"
        },
        {
          "attributes": {
            "source": {
              "id": "61616"
            }
          },
          "id": "61621",
          "type": "CDSView"
        },
        {
          "attributes": {
            "data": {},
            "selected": {
              "id": "66249"
            },
            "selection_policy": {
              "id": "66248"
            }
          },
          "id": "66211",
          "type": "ColumnDataSource"
        },
        {
          "attributes": {
            "coordinates": null,
            "end": {
              "id": "61727"
            },
            "group": null,
            "source": {
              "id": "66217"
            },
            "start": null,
            "x_end": {
              "value": 0.2222222222222222
            },
            "x_start": {
              "value": 0.2222222222222222
            },
            "y_end": {
              "value": 0.2489
            },
            "y_start": {
              "value": 0.2346
            }
          },
          "id": "61728",
          "type": "Arrow"
        },
        {
          "attributes": {
            "line_alpha": 0.1,
            "line_color": "orange",
            "line_width": 3,
            "x": {
              "field": "x"
            },
            "y": {
              "field": "y"
            }
          },
          "id": "61597",
          "type": "Line"
        },
        {
          "attributes": {
            "size": {
              "value": 10
            }
          },
          "id": "61685",
          "type": "VeeHead"
        },
        {
          "attributes": {},
          "id": "66240",
          "type": "UnionRenderers"
        },
        {
          "attributes": {
            "coordinates": null,
            "end": {
              "id": "61724"
            },
            "group": null,
            "source": {
              "id": "66216"
            },
            "start": null,
            "x_end": {
              "value": 0.2222222222222222
            },
            "x_start": {
              "value": 0.2222222222222222
            },
            "y_end": {
              "value": 0.2486
            },
            "y_start": {
              "value": 0.2332
            }
          },
          "id": "61725",
          "type": "Arrow"
        },
        {
          "attributes": {
            "axis_label": "Observed hits / at-bats",
            "coordinates": null,
            "formatter": {
              "id": "61606"
            },
            "group": null,
            "major_label_policy": {
              "id": "61607"
            },
            "minor_tick_line_color": "grey",
            "ticker": {
              "id": "61574"
            }
          },
          "id": "61573",
          "type": "LinearAxis"
        },
        {
          "attributes": {
            "data": {},
            "selected": {
              "id": "66235"
            },
            "selection_policy": {
              "id": "66234"
            }
          },
          "id": "66204",
          "type": "ColumnDataSource"
        },
        {
          "attributes": {},
          "id": "66241",
          "type": "Selection"
        },
        {
          "attributes": {
            "size": {
              "value": 10
            }
          },
          "id": "61727",
          "type": "VeeHead"
        },
        {
          "attributes": {
            "fill_alpha": {
              "value": 0.2
            },
            "fill_color": {
              "value": "white"
            },
            "hatch_alpha": {
              "value": 0.2
            },
            "line_alpha": {
              "value": 0.2
            },
            "line_color": {
              "value": "steelblue"
            },
            "size": {
              "value": 10
            },
            "x": {
              "field": "x"
            },
            "y": {
              "field": "y"
            }
          },
          "id": "61663",
          "type": "Circle"
        },
        {
          "attributes": {
            "label": {
              "value": "No-pooling"
            },
            "renderers": [
              {
                "id": "61664"
              }
            ]
          },
          "id": "61684",
          "type": "LegendItem"
        },
        {
          "attributes": {
            "fill_alpha": {
              "value": 0.1
            },
            "fill_color": {
              "value": "white"
            },
            "hatch_alpha": {
              "value": 0.1
            },
            "line_alpha": {
              "value": 0.1
            },
            "line_color": {
              "value": "steelblue"
            },
            "size": {
              "value": 10
            },
            "x": {
              "field": "x"
            },
            "y": {
              "field": "y"
            }
          },
          "id": "61662",
          "type": "Circle"
        },
        {
          "attributes": {
            "line_alpha": 0.7,
            "line_color": "grey",
            "line_width": 2.0,
            "x": {
              "field": "x"
            },
            "y": {
              "field": "y"
            }
          },
          "id": "61617",
          "type": "Line"
        },
        {
          "attributes": {
            "coordinates": null,
            "data_source": {
              "id": "61561"
            },
            "glyph": {
              "id": "61661"
            },
            "group": null,
            "hover_glyph": null,
            "muted_glyph": {
              "id": "61663"
            },
            "nonselection_glyph": {
              "id": "61662"
            },
            "view": {
              "id": "61665"
            }
          },
          "id": "61664",
          "type": "GlyphRenderer"
        },
        {
          "attributes": {},
          "id": "66242",
          "type": "UnionRenderers"
        },
        {
          "attributes": {
            "source": {
              "id": "61560"
            }
          },
          "id": "61642",
          "type": "CDSView"
        },
        {
          "attributes": {
            "coordinates": null,
            "data_source": {
              "id": "61616"
            },
            "glyph": {
              "id": "61617"
            },
            "group": null,
            "hover_glyph": null,
            "muted_glyph": {
              "id": "61619"
            },
            "nonselection_glyph": {
              "id": "61618"
            },
            "view": {
              "id": "61621"
            }
          },
          "id": "61620",
          "type": "GlyphRenderer"
        },
        {
          "attributes": {},
          "id": "66243",
          "type": "Selection"
        },
        {
          "attributes": {},
          "id": "66244",
          "type": "UnionRenderers"
        },
        {
          "attributes": {},
          "id": "61635",
          "type": "Selection"
        },
        {
          "attributes": {},
          "id": "66245",
          "type": "Selection"
        },
        {
          "attributes": {
            "data": {},
            "selected": {
              "id": "66251"
            },
            "selection_policy": {
              "id": "66250"
            }
          },
          "id": "66212",
          "type": "ColumnDataSource"
        },
        {
          "attributes": {},
          "id": "61634",
          "type": "UnionRenderers"
        },
        {
          "attributes": {
            "data": {
              "lower_std": [
                0.19579366238731277,
                0.19579366238731277,
                0.19579366238731277,
                0.19579366238731277,
                0.19579366238731277,
                0.19579366238731277,
                0.19579366238731277,
                0.19579366238731277,
                0.19579366238731277,
                0.19579366238731277,
                0.19579366238731277,
                0.19579366238731277,
                0.19579366238731277,
                0.19579366238731277,
                0.19579366238731277,
                0.19579366238731277,
                0.19579366238731277,
                0.19579366238731277
              ],
              "upper_std": [
                0.33507053514355156,
                0.33507053514355156,
                0.33507053514355156,
                0.33507053514355156,
                0.33507053514355156,
                0.33507053514355156,
                0.33507053514355156,
                0.33507053514355156,
                0.33507053514355156,
                0.33507053514355156,
                0.33507053514355156,
                0.33507053514355156,
                0.33507053514355156,
                0.33507053514355156,
                0.33507053514355156,
                0.33507053514355156,
                0.33507053514355156,
                0.33507053514355156
              ],
              "x": {
                "__ndarray__": "mpmZmZmZ2T/Ygi3Ygi3YPxdswRZswdY/VVVVVVVV1T+UPumTPunTP5Q+6ZM+6dM/0id90id90j8RERERERHRP5/0SZ/0Sc8/n/RJn/RJzz8cx3Ecx3HMPxzHcRzHccw/HMdxHMdxzD8cx3Ecx3HMPxzHcRzHccw/mpmZmZmZyT8XbMEWbMHGP5Q+6ZM+6cM/",
                "dtype": "float64",
                "order": "little",
                "shape": [
                  18
                ]
              }
            },
            "selected": {
              "id": "61635"
            },
            "selection_policy": {
              "id": "61634"
            }
          },
          "id": "61613",
          "type": "ColumnDataSource"
        },
        {
          "attributes": {},
          "id": "66246",
          "type": "UnionRenderers"
        },
        {
          "attributes": {
            "data": {
              "x": {
                "__ndarray__": "mpmZmZmZ2T/Ygi3Ygi3YPxdswRZswdY/VVVVVVVV1T+UPumTPunTP5Q+6ZM+6dM/0id90id90j8RERERERHRP5/0SZ/0Sc8/n/RJn/RJzz8cx3Ecx3HMPxzHcRzHccw/HMdxHMdxzD8cx3Ecx3HMPxzHcRzHccw/mpmZmZmZyT8XbMEWbMHGP5Q+6ZM+6cM/",
                "dtype": "float64",
                "order": "little",
                "shape": [
                  18
                ]
              },
              "y": {
                "__ndarray__": "mpmZmZmZ2T/Ygi3Ygi3YPxdswRZswdY/VVVVVVVV1T+UPumTPunTP5Q+6ZM+6dM/0id90id90j8RERERERHRP5/0SZ/0Sc8/n/RJn/RJzz8cx3Ecx3HMPxzHcRzHccw/HMdxHMdxzD8cx3Ecx3HMPxzHcRzHccw/mpmZmZmZyT8XbMEWbMHGP5Q+6ZM+6cM/",
                "dtype": "float64",
                "order": "little",
                "shape": [
                  18
                ]
              }
            },
            "selected": {
              "id": "61632"
            },
            "selection_policy": {
              "id": "61631"
            }
          },
          "id": "61616",
          "type": "ColumnDataSource"
        },
        {
          "attributes": {},
          "id": "66247",
          "type": "Selection"
        },
        {
          "attributes": {},
          "id": "66248",
          "type": "UnionRenderers"
        },
        {
          "attributes": {},
          "id": "61680",
          "type": "Selection"
        },
        {
          "attributes": {
            "line_alpha": 0.2,
            "line_color": "grey",
            "line_width": 2.0,
            "x": {
              "field": "x"
            },
            "y": {
              "field": "y"
            }
          },
          "id": "61619",
          "type": "Line"
        },
        {
          "attributes": {},
          "id": "66249",
          "type": "Selection"
        },
        {
          "attributes": {
            "line_color": "orange",
            "line_width": 3,
            "x": {
              "field": "x"
            },
            "y": {
              "field": "y"
            }
          },
          "id": "61596",
          "type": "Line"
        },
        {
          "attributes": {},
          "id": "66250",
          "type": "UnionRenderers"
        },
        {
          "attributes": {
            "size": {
              "value": 10
            }
          },
          "id": "61718",
          "type": "VeeHead"
        },
        {
          "attributes": {
            "fill_alpha": {
              "value": 0.2
            },
            "fill_color": {
              "value": "steelblue"
            },
            "hatch_alpha": {
              "value": 0.2
            },
            "line_alpha": {
              "value": 0.2
            },
            "line_color": {
              "value": "white"
            },
            "size": {
              "value": 10
            },
            "x": {
              "field": "x"
            },
            "y": {
              "field": "y"
            }
          },
          "id": "61640",
          "type": "Circle"
        },
        {
          "attributes": {},
          "id": "66251",
          "type": "Selection"
        },
        {
          "attributes": {
            "label": {
              "value": "Current hits / Current at-bats"
            },
            "renderers": [
              {
                "id": "61620"
              }
            ]
          },
          "id": "61636",
          "type": "LegendItem"
        },
        {
          "attributes": {
            "coordinates": null,
            "end": {
              "id": "61694"
            },
            "group": null,
            "source": {
              "id": "66206"
            },
            "start": null,
            "x_end": {
              "value": 0.3333333333333333
            },
            "x_start": {
              "value": 0.3333333333333333
            },
            "y_end": {
              "value": 0.2953
            },
            "y_start": {
              "value": 0.3401
            }
          },
          "id": "61695",
          "type": "Arrow"
        },
        {
          "attributes": {},
          "id": "66252",
          "type": "UnionRenderers"
        },
        {
          "attributes": {
            "coordinates": null,
            "end": {
              "id": "61700"
            },
            "group": null,
            "source": {
              "id": "66208"
            },
            "start": null,
            "x_end": {
              "value": 0.3111111111111111
            },
            "x_start": {
              "value": 0.3111111111111111
            },
            "y_end": {
              "value": 0.2855
            },
            "y_start": {
              "value": 0.3213
            }
          },
          "id": "61701",
          "type": "Arrow"
        },
        {
          "attributes": {
            "size": {
              "value": 10
            }
          },
          "id": "61733",
          "type": "VeeHead"
        },
        {
          "attributes": {},
          "id": "66253",
          "type": "Selection"
        },
        {
          "attributes": {
            "fill_color": {
              "value": "steelblue"
            },
            "line_color": {
              "value": "white"
            },
            "size": {
              "value": 10
            },
            "x": {
              "field": "x"
            },
            "y": {
              "field": "y"
            }
          },
          "id": "61638",
          "type": "Circle"
        },
        {
          "attributes": {},
          "id": "66254",
          "type": "UnionRenderers"
        },
        {
          "attributes": {},
          "id": "66255",
          "type": "Selection"
        },
        {
          "attributes": {
            "data": {},
            "selected": {
              "id": "66255"
            },
            "selection_policy": {
              "id": "66254"
            }
          },
          "id": "66214",
          "type": "ColumnDataSource"
        },
        {
          "attributes": {
            "data": {},
            "selected": {
              "id": "66253"
            },
            "selection_policy": {
              "id": "66252"
            }
          },
          "id": "66213",
          "type": "ColumnDataSource"
        },
        {
          "attributes": {
            "size": {
              "value": 10
            }
          },
          "id": "61721",
          "type": "VeeHead"
        },
        {
          "attributes": {},
          "id": "66256",
          "type": "UnionRenderers"
        },
        {
          "attributes": {
            "data": {},
            "selected": {
              "id": "66239"
            },
            "selection_policy": {
              "id": "66238"
            }
          },
          "id": "66206",
          "type": "ColumnDataSource"
        },
        {
          "attributes": {
            "coordinates": null,
            "end": {
              "id": "61718"
            },
            "group": null,
            "source": {
              "id": "66214"
            },
            "start": null,
            "x_end": {
              "value": 0.2222222222222222
            },
            "x_start": {
              "value": 0.2222222222222222
            },
            "y_end": {
              "value": 0.2491
            },
            "y_start": {
              "value": 0.2326
            }
          },
          "id": "61719",
          "type": "Arrow"
        },
        {
          "attributes": {
            "size": {
              "value": 10
            }
          },
          "id": "61709",
          "type": "VeeHead"
        },
        {
          "attributes": {
            "size": {
              "value": 10
            }
          },
          "id": "61724",
          "type": "VeeHead"
        },
        {
          "attributes": {},
          "id": "66257",
          "type": "Selection"
        },
        {
          "attributes": {
            "coordinates": null,
            "end": {
              "id": "61715"
            },
            "group": null,
            "source": {
              "id": "66213"
            },
            "start": null,
            "x_end": {
              "value": 0.2222222222222222
            },
            "x_start": {
              "value": 0.2222222222222222
            },
            "y_end": {
              "value": 0.2492
            },
            "y_start": {
              "value": 0.235
            }
          },
          "id": "61716",
          "type": "Arrow"
        },
        {
          "attributes": {},
          "id": "61604",
          "type": "AllLabels"
        },
        {
          "attributes": {
            "data": {},
            "selected": {
              "id": "66259"
            },
            "selection_policy": {
              "id": "66258"
            }
          },
          "id": "66216",
          "type": "ColumnDataSource"
        },
        {
          "attributes": {
            "fill_alpha": {
              "value": 0.1
            },
            "fill_color": {
              "value": "steelblue"
            },
            "hatch_alpha": {
              "value": 0.1
            },
            "line_alpha": {
              "value": 0.1
            },
            "line_color": {
              "value": "white"
            },
            "size": {
              "value": 10
            },
            "x": {
              "field": "x"
            },
            "y": {
              "field": "y"
            }
          },
          "id": "61639",
          "type": "Circle"
        },
        {
          "attributes": {},
          "id": "66258",
          "type": "UnionRenderers"
        },
        {
          "attributes": {
            "coordinates": null,
            "end": {
              "id": "61688"
            },
            "group": null,
            "source": {
              "id": "66204"
            },
            "start": null,
            "x_end": {
              "value": 0.37777777777777777
            },
            "x_start": {
              "value": 0.37777777777777777
            },
            "y_end": {
              "value": 0.3138
            },
            "y_start": {
              "value": 0.3824
            }
          },
          "id": "61689",
          "type": "Arrow"
        },
        {
          "attributes": {},
          "id": "61571",
          "type": "LinearScale"
        },
        {
          "attributes": {},
          "id": "61608",
          "type": "UnionRenderers"
        },
        {
          "attributes": {},
          "id": "66259",
          "type": "Selection"
        },
        {
          "attributes": {
            "line_alpha": 0.2,
            "line_color": "orange",
            "line_width": 3,
            "x": {
              "field": "x"
            },
            "y": {
              "field": "y"
            }
          },
          "id": "61598",
          "type": "Line"
        },
        {
          "attributes": {
            "size": {
              "value": 10
            }
          },
          "id": "61712",
          "type": "VeeHead"
        },
        {
          "attributes": {
            "source": {
              "id": "61595"
            }
          },
          "id": "61600",
          "type": "CDSView"
        },
        {
          "attributes": {},
          "id": "66260",
          "type": "UnionRenderers"
        },
        {
          "attributes": {
            "coordinates": null,
            "end": {
              "id": "61685"
            },
            "group": null,
            "source": {
              "id": "66203"
            },
            "start": null,
            "x_end": {
              "value": 0.4
            },
            "x_start": {
              "value": 0.4
            },
            "y_end": {
              "value": 0.3231
            },
            "y_start": {
              "value": 0.405
            }
          },
          "id": "61686",
          "type": "Arrow"
        },
        {
          "attributes": {},
          "id": "66261",
          "type": "Selection"
        },
        {
          "attributes": {
            "size": {
              "value": 10
            }
          },
          "id": "61715",
          "type": "VeeHead"
        },
        {
          "attributes": {
            "coordinates": null,
            "end": {
              "id": "61706"
            },
            "group": null,
            "source": {
              "id": "66210"
            },
            "start": null,
            "x_end": {
              "value": 0.26666666666666666
            },
            "x_start": {
              "value": 0.26666666666666666
            },
            "y_end": {
              "value": 0.2674
            },
            "y_start": {
              "value": 0.2758
            }
          },
          "id": "61707",
          "type": "Arrow"
        },
        {
          "attributes": {},
          "id": "61655",
          "type": "Selection"
        },
        {
          "attributes": {},
          "id": "61586",
          "type": "HelpTool"
        },
        {
          "attributes": {},
          "id": "61606",
          "type": "BasicTickFormatter"
        },
        {
          "attributes": {
            "size": {
              "value": 10
            }
          },
          "id": "61697",
          "type": "VeeHead"
        },
        {
          "attributes": {},
          "id": "66262",
          "type": "UnionRenderers"
        },
        {
          "attributes": {
            "coordinates": null,
            "end": {
              "id": "61703"
            },
            "group": null,
            "source": {
              "id": "66209"
            },
            "start": null,
            "x_end": {
              "value": 0.28888888888888886
            },
            "x_start": {
              "value": 0.28888888888888886
            },
            "y_end": {
              "value": 0.2765
            },
            "y_start": {
              "value": 0.2998
            }
          },
          "id": "61704",
          "type": "Arrow"
        },
        {
          "attributes": {},
          "id": "66263",
          "type": "Selection"
        },
        {
          "attributes": {
            "coordinates": null,
            "end": {
              "id": "61736"
            },
            "group": null,
            "source": {
              "id": "66220"
            },
            "start": null,
            "x_end": {
              "value": 0.15555555555555556
            },
            "x_start": {
              "value": 0.15555555555555556
            },
            "y_end": {
              "value": 0.2207
            },
            "y_start": {
              "value": 0.1696
            }
          },
          "id": "61737",
          "type": "Arrow"
        },
        {
          "attributes": {},
          "id": "61654",
          "type": "UnionRenderers"
        },
        {
          "attributes": {
            "coordinates": null,
            "end": {
              "id": "61712"
            },
            "group": null,
            "source": {
              "id": "66212"
            },
            "start": null,
            "x_end": {
              "value": 0.24444444444444444
            },
            "x_start": {
              "value": 0.24444444444444444
            },
            "y_end": {
              "value": 0.2575
            },
            "y_start": {
              "value": 0.2545
            }
          },
          "id": "61713",
          "type": "Arrow"
        },
        {
          "attributes": {
            "coordinates": null,
            "end": {
              "id": "61721"
            },
            "group": null,
            "source": {
              "id": "66215"
            },
            "start": null,
            "x_end": {
              "value": 0.2222222222222222
            },
            "x_start": {
              "value": 0.2222222222222222
            },
            "y_end": {
              "value": 0.2486
            },
            "y_start": {
              "value": 0.2339
            }
          },
          "id": "61722",
          "type": "Arrow"
        },
        {
          "attributes": {},
          "id": "61578",
          "type": "BasicTicker"
        },
        {
          "attributes": {},
          "id": "66264",
          "type": "UnionRenderers"
        },
        {
          "attributes": {
            "size": {
              "value": 10
            }
          },
          "id": "61688",
          "type": "VeeHead"
        },
        {
          "attributes": {
            "data": {},
            "selected": {
              "id": "66233"
            },
            "selection_policy": {
              "id": "66232"
            }
          },
          "id": "66203",
          "type": "ColumnDataSource"
        },
        {
          "attributes": {
            "data": {},
            "selected": {
              "id": "66261"
            },
            "selection_policy": {
              "id": "66260"
            }
          },
          "id": "66217",
          "type": "ColumnDataSource"
        },
        {
          "attributes": {},
          "id": "66265",
          "type": "Selection"
        },
        {
          "attributes": {},
          "id": "61603",
          "type": "BasicTickFormatter"
        },
        {
          "attributes": {
            "size": {
              "value": 10
            }
          },
          "id": "61736",
          "type": "VeeHead"
        },
        {
          "attributes": {
            "coordinates": null,
            "end": {
              "id": "61691"
            },
            "group": null,
            "source": {
              "id": "66205"
            },
            "start": null,
            "x_end": {
              "value": 0.35555555555555557
            },
            "x_start": {
              "value": 0.35555555555555557
            },
            "y_end": {
              "value": 0.3047
            },
            "y_start": {
              "value": 0.3636
            }
          },
          "id": "61692",
          "type": "Arrow"
        },
        {
          "attributes": {
            "coordinates": null,
            "data_source": {
              "id": "61595"
            },
            "glyph": {
              "id": "61596"
            },
            "group": null,
            "hover_glyph": null,
            "level": "underlay",
            "muted_glyph": {
              "id": "61598"
            },
            "nonselection_glyph": {
              "id": "61597"
            },
            "view": {
              "id": "61600"
            }
          },
          "id": "61599",
          "type": "GlyphRenderer"
        },
        {
          "attributes": {
            "label": {
              "value": "Population mean"
            },
            "renderers": [
              {
                "id": "61599"
              }
            ]
          },
          "id": "61612",
          "type": "LegendItem"
        },
        {
          "attributes": {},
          "id": "66266",
          "type": "UnionRenderers"
        },
        {
          "attributes": {
            "label": {
              "value": "Partial-pooling"
            },
            "renderers": [
              {
                "id": "61641"
              }
            ]
          },
          "id": "61659",
          "type": "LegendItem"
        },
        {
          "attributes": {},
          "id": "66267",
          "type": "Selection"
        },
        {
          "attributes": {
            "size": {
              "value": 10
            }
          },
          "id": "61700",
          "type": "VeeHead"
        },
        {
          "attributes": {
            "source": {
              "id": "61561"
            }
          },
          "id": "61665",
          "type": "CDSView"
        },
        {
          "attributes": {
            "size": {
              "value": 10
            }
          },
          "id": "61691",
          "type": "VeeHead"
        },
        {
          "attributes": {
            "fill_color": {
              "value": "white"
            },
            "line_color": {
              "value": "steelblue"
            },
            "size": {
              "value": 10
            },
            "x": {
              "field": "x"
            },
            "y": {
              "field": "y"
            }
          },
          "id": "61661",
          "type": "Circle"
        },
        {
          "attributes": {
            "coordinates": null,
            "data_source": {
              "id": "61560"
            },
            "glyph": {
              "id": "61638"
            },
            "group": null,
            "hover_glyph": null,
            "muted_glyph": {
              "id": "61640"
            },
            "nonselection_glyph": {
              "id": "61639"
            },
            "view": {
              "id": "61642"
            }
          },
          "id": "61641",
          "type": "GlyphRenderer"
        },
        {
          "attributes": {},
          "id": "61585",
          "type": "ResetTool"
        },
        {
          "attributes": {
            "data": {},
            "selected": {
              "id": "66237"
            },
            "selection_policy": {
              "id": "66236"
            }
          },
          "id": "66205",
          "type": "ColumnDataSource"
        },
        {
          "attributes": {
            "data": {},
            "selected": {
              "id": "66257"
            },
            "selection_policy": {
              "id": "66256"
            }
          },
          "id": "66215",
          "type": "ColumnDataSource"
        },
        {
          "attributes": {
            "coordinates": null,
            "end": {
              "id": "61733"
            },
            "group": null,
            "source": {
              "id": "66219"
            },
            "start": null,
            "x_end": {
              "value": 0.17777777777777778
            },
            "x_start": {
              "value": 0.17777777777777778
            },
            "y_end": {
              "value": 0.2303
            },
            "y_start": {
              "value": 0.1916
            }
          },
          "id": "61734",
          "type": "Arrow"
        },
        {
          "attributes": {},
          "id": "61584",
          "type": "SaveTool"
        },
        {
          "attributes": {
            "data": {},
            "selected": {
              "id": "66263"
            },
            "selection_policy": {
              "id": "66262"
            }
          },
          "id": "66218",
          "type": "ColumnDataSource"
        },
        {
          "attributes": {
            "coordinates": null,
            "end": {
              "id": "61730"
            },
            "group": null,
            "source": {
              "id": "66218"
            },
            "start": null,
            "x_end": {
              "value": 0.2
            },
            "x_start": {
              "value": 0.2
            },
            "y_end": {
              "value": 0.2394
            },
            "y_start": {
              "value": 0.2117
            }
          },
          "id": "61731",
          "type": "Arrow"
        },
        {
          "attributes": {
            "coordinates": null,
            "group": null,
            "text": "Partial pooling shift"
          },
          "id": "61563",
          "type": "Title"
        },
        {
          "attributes": {
            "data": {},
            "selected": {
              "id": "66265"
            },
            "selection_policy": {
              "id": "66264"
            }
          },
          "id": "66219",
          "type": "ColumnDataSource"
        },
        {
          "attributes": {
            "bottom_units": "screen",
            "coordinates": null,
            "fill_alpha": 0.5,
            "fill_color": "lightgrey",
            "group": null,
            "left_units": "screen",
            "level": "overlay",
            "line_alpha": 1.0,
            "line_color": "black",
            "line_dash": [
              4,
              4
            ],
            "line_width": 2,
            "right_units": "screen",
            "syncable": false,
            "top_units": "screen"
          },
          "id": "61587",
          "type": "BoxAnnotation"
        },
        {
          "attributes": {
            "data": {
              "name": [
                "Roberto Clemente",
                "Frank Robinson",
                "Frank Howard",
                "Jay Johnstone",
                "Ken Berry",
                "Jim Spencer",
                "Don Kessinger",
                "Luis Alvarado",
                "Ron Santo",
                "Ron Swaboda",
                "Rico Petrocelli",
                "Ellie Rodriguez",
                "George Scott",
                "Del Unser",
                "Billy Williams",
                "Bert Campaneris",
                "Thurman Munson",
                "Max Alvis"
              ],
              "x": {
                "__ndarray__": "mpmZmZmZ2T/Ygi3Ygi3YPxdswRZswdY/VVVVVVVV1T+UPumTPunTP5Q+6ZM+6dM/0id90id90j8RERERERHRP5/0SZ/0Sc8/n/RJn/RJzz8cx3Ecx3HMPxzHcRzHccw/HMdxHMdxzD8cx3Ecx3HMPxzHcRzHccw/mpmZmZmZyT8XbMEWbMHGP5Q+6ZM+6cM/",
                "dtype": "float64",
                "order": "little",
                "shape": [
                  18
                ]
              },
              "y": {
                "__ndarray__": "7FG4HoXr2T+3Yn/ZPXnYP6HWNO84Rdc/h6dXyjLE1T9xGw3gLZDUP3EbDeAtkNQ/q8/VVuwv0z+7Jw8LtabRP1K4HoXrUdA/fT81XrpJ0D8UrkfhehTOP0tZhjjWxc0/OGdEaW/wzT99rrZif9nNP/Mf0m9fB84/8BZIUPwYyz/Y8PRKWYbIP6Fns+pztcU/",
                "dtype": "float64",
                "order": "little",
                "shape": [
                  18
                ]
              }
            },
            "selected": {
              "id": "61680"
            },
            "selection_policy": {
              "id": "61679"
            }
          },
          "id": "61561",
          "type": "ColumnDataSource"
        },
        {
          "attributes": {
            "size": {
              "value": 10
            }
          },
          "id": "61703",
          "type": "VeeHead"
        },
        {
          "attributes": {
            "end": 0.41,
            "start": 0.14
          },
          "id": "61565",
          "type": "Range1d"
        },
        {
          "attributes": {
            "axis": {
              "id": "61577"
            },
            "coordinates": null,
            "dimension": 1,
            "grid_line_alpha": 0.2,
            "grid_line_color": "grey",
            "grid_line_width": 0.2,
            "group": null,
            "ticker": null
          },
          "id": "61580",
          "type": "Grid"
        },
        {
          "attributes": {
            "data": {},
            "selected": {
              "id": "66267"
            },
            "selection_policy": {
              "id": "66266"
            }
          },
          "id": "66220",
          "type": "ColumnDataSource"
        },
        {
          "attributes": {
            "size": {
              "value": 10
            }
          },
          "id": "61706",
          "type": "VeeHead"
        },
        {
          "attributes": {
            "coordinates": null,
            "end": {
              "id": "61697"
            },
            "group": null,
            "source": {
              "id": "66207"
            },
            "start": null,
            "x_end": {
              "value": 0.3111111111111111
            },
            "x_start": {
              "value": 0.3111111111111111
            },
            "y_end": {
              "value": 0.2859
            },
            "y_start": {
              "value": 0.3213
            }
          },
          "id": "61698",
          "type": "Arrow"
        },
        {
          "attributes": {
            "tools": [
              {
                "id": "61581"
              },
              {
                "id": "61582"
              },
              {
                "id": "61583"
              },
              {
                "id": "61584"
              },
              {
                "id": "61585"
              },
              {
                "id": "61586"
              }
            ]
          },
          "id": "61588",
          "type": "Toolbar"
        },
        {
          "attributes": {
            "data": {
              "x": [
                0,
                1
              ],
              "y": [
                0.26543209876543217,
                0.26543209876543217
              ]
            },
            "selected": {
              "id": "61609"
            },
            "selection_policy": {
              "id": "61608"
            }
          },
          "id": "61595",
          "type": "ColumnDataSource"
        },
        {
          "attributes": {},
          "id": "61581",
          "type": "PanTool"
        },
        {
          "attributes": {
            "axis": {
              "id": "61573"
            },
            "coordinates": null,
            "grid_line_alpha": 0.2,
            "grid_line_color": "grey",
            "grid_line_width": 0.2,
            "group": null,
            "ticker": null
          },
          "id": "61576",
          "type": "Grid"
        },
        {
          "attributes": {
            "axis_label": "Predicted chance of a hit",
            "coordinates": null,
            "formatter": {
              "id": "61603"
            },
            "group": null,
            "major_label_policy": {
              "id": "61604"
            },
            "minor_tick_line_color": "grey",
            "ticker": {
              "id": "61578"
            }
          },
          "id": "61577",
          "type": "LinearAxis"
        },
        {
          "attributes": {},
          "id": "61632",
          "type": "Selection"
        },
        {
          "attributes": {},
          "id": "66232",
          "type": "UnionRenderers"
        },
        {
          "attributes": {
            "overlay": {
              "id": "61587"
            }
          },
          "id": "61583",
          "type": "BoxZoomTool"
        },
        {
          "attributes": {},
          "id": "61569",
          "type": "LinearScale"
        },
        {
          "attributes": {},
          "id": "61582",
          "type": "WheelZoomTool"
        },
        {
          "attributes": {},
          "id": "66233",
          "type": "Selection"
        },
        {
          "attributes": {
            "click_policy": "mute",
            "coordinates": null,
            "group": null,
            "items": [
              {
                "id": "61612"
              },
              {
                "id": "61636"
              },
              {
                "id": "61659"
              },
              {
                "id": "61684"
              }
            ],
            "location": "top_left"
          },
          "id": "61611",
          "type": "Legend"
        },
        {
          "attributes": {},
          "id": "61574",
          "type": "BasicTicker"
        },
        {
          "attributes": {
            "end": 0.55,
            "start": 0.05
          },
          "id": "61567",
          "type": "Range1d"
        },
        {
          "attributes": {},
          "id": "61679",
          "type": "UnionRenderers"
        }
      ],
      "root_ids": [
        "61562"
      ]
    },
    "title": "Bokeh Application",
    "version": "2.4.2"
  },
  "version": "2.4.2"
}